Metadata-Version: 2.1
Name: aggPy
Version: 0.3.0
Summary: Calculate network properties from MD trajectory
Home-page: https://github.com/Corcellilab/Phosphates/tree/main/aggPy
Author: Noah Vasconez
Author-email: nvascone@nd.edu
License: Permission is hereby granted, free of charge, to any person obtaining a copy of this software and associated documentation files (the "Software"), to deal in the Software without restriction, including without limitation the rights to use, copy, modify, merge, publish, distribute, sublicense, and/or sell copies of the Software, and to permit persons to whom the Software is furnished to do so, subject to the following conditions: The above copyright notice and this permission notice shal
Classifier: Development Status :: 1 - Planning
Classifier: Intended Audience :: Science/Research
Classifier: Programming Language :: Python :: 3.12
Requires-Dist: MDAnalysis
Requires-Dist: numpy
Requires-Dist: pandas
Requires-Dist: networkx
